maid/__init__.py
maid/__main__.py
maid/config.py
maid/core.py
maid/error.py
maid/maid.py
maid/pkgman.py
maid/run.py
maid/version.py
maid-0.1.12.dist-info/LICENSE
maid-0.1.12.dist-info/METADATA
maid-0.1.12.dist-info/WHEEL
maid-0.1.12.dist-info/top_level.txt
maid-0.1.12.dist-info/RECORD
