Metadata-Version: 2.1
Name: maid
Version: 0.1.12
Summary: A package manager written in Python 3.7
Home-page: https://github.com/dungwinux/Maid
Author: Nguyễn Tuấn Dũng
Author-email: ntddebugger@gmail.com
License: UNKNOWN
Platform: UNKNOWN
Classifier: Development Status :: 3 - Alpha
Classifier: Operating System :: Microsoft :: Windows :: Windows 7
Classifier: Operating System :: Microsoft :: Windows :: Windows 8
Classifier: Operating System :: Microsoft :: Windows :: Windows 8.1
Classifier: Operating System :: Microsoft :: Windows :: Windows 10
Classifier: Programming Language :: Python :: 3.7
Classifier: License :: OSI Approved :: GNU General Public License v3 (GPLv3)
Classifier: Operating System :: Microsoft :: Windows
Requires-Dist: wget (>=3.2)
Requires-Dist: patool (>=1.12)
Requires-Dist: pywin32 (>=224)
Requires-Dist: winshell (>=0.6)
